agentkernel_distributed/__init__.py
agentkernel_distributed/mas/__init__.py
agentkernel_distributed/mas/builder.py
agentkernel_distributed/mas/action/__init__.py
agentkernel_distributed/mas/action/action.py
agentkernel_distributed/mas/action/base/__init__.py
agentkernel_distributed/mas/action/base/component_base.py
agentkernel_distributed/mas/action/base/plugin_base.py
agentkernel_distributed/mas/action/components/__init__.py
agentkernel_distributed/mas/action/components/communication.py
agentkernel_distributed/mas/action/components/otheractions.py
agentkernel_distributed/mas/action/components/tools.py
agentkernel_distributed/mas/agent/__init__.py
agentkernel_distributed/mas/agent/agent.py
agentkernel_distributed/mas/agent/agent_manager.py
agentkernel_distributed/mas/agent/base/__init__.py
agentkernel_distributed/mas/agent/base/component_base.py
agentkernel_distributed/mas/agent/base/plugin_base.py
agentkernel_distributed/mas/agent/components/__init__.py
agentkernel_distributed/mas/agent/components/invoke.py
agentkernel_distributed/mas/agent/components/perceive.py
agentkernel_distributed/mas/agent/components/plan.py
agentkernel_distributed/mas/agent/components/profile.py
agentkernel_distributed/mas/agent/components/reflect.py
agentkernel_distributed/mas/agent/components/state.py
agentkernel_distributed/mas/controller/__init__.py
agentkernel_distributed/mas/controller/base.py
agentkernel_distributed/mas/controller/controller.py
agentkernel_distributed/mas/environment/__init__.py
agentkernel_distributed/mas/environment/environment.py
agentkernel_distributed/mas/environment/base/__init__.py
agentkernel_distributed/mas/environment/base/component_base.py
agentkernel_distributed/mas/environment/base/plugin_base.py
agentkernel_distributed/mas/environment/components/__init__.py
agentkernel_distributed/mas/environment/components/generic.py
agentkernel_distributed/mas/environment/components/relation.py
agentkernel_distributed/mas/environment/components/space.py
agentkernel_distributed-1.1.0.dist-info/METADATA
agentkernel_distributed-1.1.0.dist-info/WHEEL
agentkernel_distributed-1.1.0.dist-info/entry_points.txt
agentkernel_distributed-1.1.0.dist-info/RECORD
